pysbatch/__init__.py
pysbatch/batch_setting.py
pysbatch/hello.py
pysbatch/pysbatch.py
pysbatch-0.1.6.dist-info/LICENSE.txt
pysbatch-0.1.6.dist-info/METADATA
pysbatch-0.1.6.dist-info/RECORD
pysbatch-0.1.6.dist-info/WHEEL
pysbatch-0.1.6.dist-info/top_level.txt
