Metadata-Version: 2.1
Name: pysbatch
Version: 0.1.6
Summary: Submit slurm job in python
Home-page: https://github.com/luptior/pysbatch
Author: Gan Xu
Author-email: luptior@gmail.com
License: MIT
Keywords: slurm batch job submit
Platform: UNKNOWN
Classifier: Development Status :: 4 - Beta
Classifier: Intended Audience :: Science/Research
Classifier: Topic :: Scientific/Engineering :: Bio-Informatics
Classifier: License :: OSI Approved :: MIT License
Classifier: Programming Language :: Python :: 3.5
Classifier: Programming Language :: Python :: 3.6
Requires-Python: >=3.5
